rescalepy/__init__.py
rescalepy/__main__.py
rescalepy/batch.py
rescalepy/client.py
rescalepy/config.py
rescalepy-0.4.1.dist-info/LICENSE
rescalepy-0.4.1.dist-info/METADATA
rescalepy-0.4.1.dist-info/WHEEL
rescalepy-0.4.1.dist-info/top_level.txt
rescalepy-0.4.1.dist-info/RECORD
