Metadata-Version: 2.1
Name: rescalepy
Version: 0.4.1
Summary: a Python client library for the Rescale API
Home-page: https://github.com/bthornton191/rescalepy
Author: Ben Thornton
Author-email: bthorn191@gmail.com
Classifier: Programming Language :: Python :: 3
Classifier: License :: OSI Approved :: MIT License
Classifier: Operating System :: Microsoft :: Windows
License-File: LICENSE
Requires-Dist: requests
Requires-Dist: keyring
Requires-Dist: typing-extensions
